[
    {
        "key": "dbln",
        "value": "%7B%2261569035459991%22%3A%2205rgwNMK%22%7D",
        "domain": "facebook.com",
        "path": "/login/device-based/",
        "hostOnly": false,
        "creation": "2025-01-14T04:41:04.191Z",
        "lastAccessed": "2025-01-14T04:41:04.191Z"
    },
    {
        "key": "datr",
        "value": "RvSBZ-RSWwNFbS7gfC6xSOh0",
        "domain": "facebook.com",
        "path": "/",
        "hostOnly": false,
        "creation": "2025-01-14T04:41:04.191Z",
        "lastAccessed": "2025-01-14T04:41:04.191Z"
    },
    {
        "key": "sb",
        "value": "RvSBZ16K6ZqvISvbgNg3PH3O",
        "domain": "facebook.com",
        "path": "/",
        "hostOnly": false,
        "creation": "2025-01-14T04:41:04.191Z",
        "lastAccessed": "2025-01-14T04:41:04.191Z"
    },
    {
        "key": "ps_l",
        "value": "1",
        "domain": "facebook.com",
        "path": "/",
        "hostOnly": false,
        "creation": "2025-01-14T04:41:04.191Z",
        "lastAccessed": "2025-01-14T04:41:04.191Z"
    },
    {
        "key": "ps_n",
        "value": "1",
        "domain": "facebook.com",
        "path": "/",
        "hostOnly": false,
        "creation": "2025-01-14T04:41:04.191Z",
        "lastAccessed": "2025-01-14T04:41:04.191Z"
    },
    {
        "key": "wd",
        "value": "360x674",
        "domain": "facebook.com",
        "path": "/",
        "hostOnly": false,
        "creation": "2025-01-14T04:41:04.191Z",
        "lastAccessed": "2025-01-14T04:41:04.191Z"
    },
    {
        "key": "c_user",
        "value": "61569035459991",
        "domain": "facebook.com",
        "path": "/",
        "hostOnly": false,
        "creation": "2025-01-14T04:41:04.191Z",
        "lastAccessed": "2025-01-14T04:41:04.191Z"
    },
    {
        "key": "fr",
        "value": "0krLta6PiAEMy6W1b.AWUHbQywtZULBPCH0TkEqf_n3BU.BngfRG..AAA.0.0.BngfZE.AWVl8ssQ8dc",
        "domain": "facebook.com",
        "path": "/",
        "hostOnly": false,
        "creation": "2025-01-14T04:41:04.191Z",
        "lastAccessed": "2025-01-14T04:41:04.191Z"
    },
    {
        "key": "xs",
        "value": "14%3AJEde-ZlPq6QcYg%3A2%3A1736570438%3A-1%3A10526",
        "domain": "facebook.com",
        "path": "/",
        "hostOnly": false,
        "creation": "2025-01-14T04:41:04.191Z",
        "lastAccessed": "2025-01-14T04:41:04.191Z"
    },
    {
        "key": "locale",
        "value": "en_GB",
        "domain": "facebook.com",
        "path": "/",
        "hostOnly": false,
        "creation": "2025-01-14T04:41:04.191Z",
        "lastAccessed": "2025-01-14T04:41:04.191Z"
    },
    {
        "key": "vpd",
        "value": "v1%3B674x360x2",
        "domain": "facebook.com",
        "path": "/",
        "hostOnly": false,
        "creation": "2025-01-14T04:41:04.191Z",
        "lastAccessed": "2025-01-14T04:41:04.191Z"
    },
    {
        "key": "wl_cbv",
        "value": "v2%3Bclient_version%3A2713%3Btimestamp%3A1736829544",
        "domain": "facebook.com",
        "path": "/",
        "hostOnly": false,
        "creation": "2025-01-14T04:41:04.191Z",
        "lastAccessed": "2025-01-14T04:41:04.191Z"
    },
    {
        "key": "fbl_st",
        "value": "101624052%3BT%3A28947159",
        "domain": "facebook.com",
        "path": "/",
        "hostOnly": false,
        "creation": "2025-01-14T04:41:04.191Z",
        "lastAccessed": "2025-01-14T04:41:04.191Z"
    }
]
